cactus/__init__.py
cactus/common.py
cactus/config.py
cactus/train.py
cactus/utils.py
cactus/kernels/__init__.py
cactus/kernels/matmul.cpython-311-darwin.so
cactus/nn/__init__.py
cactus/nn/autodiff.py
cactus/nn/layers.py
cactus/nn/ops.py
cactus/nn/transformer.py
cactus_lib-0.1.5.dist-info/licenses/LICENSE
cactus_lib-0.1.5.dist-info/METADATA
cactus_lib-0.1.5.dist-info/WHEEL
cactus_lib-0.1.5.dist-info/top_level.txt
cactus_lib-0.1.5.dist-info/RECORD
