Metadata-Version: 2.4
Name: cactus-lib
Version: 0.1.5
Summary: Framework for fine-tuning LLMs on the Cactus Compute platform
Author: Cactus Compute, Inc
Classifier: Programming Language :: Python :: 3
Classifier: License :: OSI Approved :: MIT License
Classifier: Operating System :: OS Independent
License-File: LICENSE
Requires-Dist: numpy
Requires-Dist: transformers
Requires-Dist: platformdirs
Requires-Dist: tqdm
Requires-Dist: pybind11
Dynamic: author
Dynamic: classifier
Dynamic: description
Dynamic: description-content-type
Dynamic: license-file
Dynamic: requires-dist
Dynamic: summary
